odoo/addons/mail_thread_create_nolog/README.rst
odoo/addons/mail_thread_create_nolog/__init__.py
odoo/addons/mail_thread_create_nolog/__manifest__.py
odoo/addons/mail_thread_create_nolog/controllers/__init__.py
odoo/addons/mail_thread_create_nolog/controllers/thread.py
odoo/addons/mail_thread_create_nolog/i18n/es.po
odoo/addons/mail_thread_create_nolog/i18n/it.po
odoo/addons/mail_thread_create_nolog/i18n/mail_thread_create_nolog.pot
odoo/addons/mail_thread_create_nolog/models/__init__.py
odoo/addons/mail_thread_create_nolog/models/mail_message.py
odoo/addons/mail_thread_create_nolog/models/mail_thread.py
odoo/addons/mail_thread_create_nolog/readme/CONTRIBUTORS.md
odoo/addons/mail_thread_create_nolog/readme/CREDITS.md
odoo/addons/mail_thread_create_nolog/readme/DESCRIPTION.md
odoo/addons/mail_thread_create_nolog/readme/ROADMAP.md
odoo/addons/mail_thread_create_nolog/static/description/icon.png
odoo/addons/mail_thread_create_nolog/static/description/index.html
odoo/addons/mail_thread_create_nolog/tests/__init__.py
odoo/addons/mail_thread_create_nolog/tests/test_create_nolog.py
odoo_addon_mail_thread_create_nolog-18.0.1.0.2.dist-info/METADATA
odoo_addon_mail_thread_create_nolog-18.0.1.0.2.dist-info/WHEEL
odoo_addon_mail_thread_create_nolog-18.0.1.0.2.dist-info/top_level.txt
odoo_addon_mail_thread_create_nolog-18.0.1.0.2.dist-info/RECORD
